{"ดงพระราม": [{"date": "2026-03-16", "note": "Visited community center"}], "บ้านทาม": [{"date": "2026-03-16", "note": "Meeting local leaders"}, {"date": "2026-03-10", "note": "Previous check"}, {"date": "2026-03-05", "note": "Initial planning"}, {"date": "2026-03-01", "note": "First contact"}], "หนองโพรง": [{"date": "2026-03-12", "note": "Follow up"}, {"date": "2026-03-14", "note": "Second follow up"}], "ท่าตูม": [{"date": "2026-03-15", "note": "Door-to-door check"}], "ศรีมหาโพธิ": [{"date": "2026-03-11", "note": "City hall visit"}, {"date": "2026-03-01", "note": "Met mayor"}], "โคกปีบ": [{"date": "2026-02-28", "note": "Event"}, {"date": "2026-03-02", "note": "Followup"}, {"date": "2026-03-05", "note": "Another event"}, {"date": "2026-03-10", "note": "Visit 4"}]}